postgres_mcp/__init__.py
postgres_mcp/artifacts.py
postgres_mcp/server.py
postgres_mcp/tool_filtering.py
postgres_mcp/backup/__init__.py
postgres_mcp/backup/backup_tools.py
postgres_mcp/database_health/__init__.py
postgres_mcp/database_health/buffer_health_calc.py
postgres_mcp/database_health/connection_health_calc.py
postgres_mcp/database_health/constraint_health_calc.py
postgres_mcp/database_health/database_health.py
postgres_mcp/database_health/index_health_calc.py
postgres_mcp/database_health/replication_calc.py
postgres_mcp/database_health/sequence_health_calc.py
postgres_mcp/database_health/vacuum_health_calc.py
postgres_mcp/explain/README.md
postgres_mcp/explain/__init__.py
postgres_mcp/explain/explain_plan.py
postgres_mcp/geo/__init__.py
postgres_mcp/geo/geo_tools.py
postgres_mcp/index/dta_calc.py
postgres_mcp/index/index_opt_base.py
postgres_mcp/index/llm_opt.py
postgres_mcp/index/presentation.py
postgres_mcp/json/__init__.py
postgres_mcp/json/json_advanced_tools.py
postgres_mcp/json/json_helper_tools.py
postgres_mcp/monitoring/__init__.py
postgres_mcp/monitoring/monitoring_tools.py
postgres_mcp/performance/__init__.py
postgres_mcp/performance/performance_tools.py
postgres_mcp/resources/__init__.py
postgres_mcp/resources/database_resources.py
postgres_mcp/resources/prompt_handlers.py
postgres_mcp/sql/__init__.py
postgres_mcp/sql/bind_params.py
postgres_mcp/sql/extension_utils.py
postgres_mcp/sql/index.py
postgres_mcp/sql/safe_sql.py
postgres_mcp/sql/sql_driver.py
postgres_mcp/statistics/__init__.py
postgres_mcp/statistics/statistical_tools.py
postgres_mcp/text/__init__.py
postgres_mcp/text/text_processing_tools.py
postgres_mcp/top_queries/__init__.py
postgres_mcp/top_queries/top_queries_calc.py
postgres_mcp/vector/__init__.py
postgres_mcp/vector/vector_tools.py
postgres_mcp_enhanced-1.2.0.dist-info/METADATA
postgres_mcp_enhanced-1.2.0.dist-info/WHEEL
postgres_mcp_enhanced-1.2.0.dist-info/entry_points.txt
postgres_mcp_enhanced-1.2.0.dist-info/licenses/LICENSE
postgres_mcp_enhanced-1.2.0.dist-info/RECORD
