Metadata-Version: 2.4
Name: postgres-mcp-enhanced
Version: 1.2.0
Summary: Enterprise PostgreSQL MCP Server - Enhanced fork with comprehensive security, AI-native operations, and intelligent meta-awareness
Project-URL: Homepage, https://github.com/neverinfamous/postgres-mcp
Project-URL: Repository, https://github.com/neverinfamous/postgres-mcp
Project-URL: Issues, https://github.com/neverinfamous/postgres-mcp/issues
Project-URL: Documentation, https://github.com/neverinfamous/postgres-mcp/wiki
Author-email: Chris LeRoux <admin@adamic.tech>
License-Expression: MIT
License-File: LICENSE
Keywords: database,mcp,model-context-protocol,pgvector,postgis,postgres,postgresql
Classifier: Development Status :: 5 - Production/Stable
Classifier: Intended Audience :: Developers
Classifier: License :: OSI Approved :: MIT License
Classifier: Operating System :: OS Independent
Classifier: Programming Language :: Python :: 3
Classifier: Programming Language :: Python :: 3.12
Classifier: Programming Language :: Python :: 3.13
Classifier: Programming Language :: Python :: 3.14
Classifier: Topic :: Database
Classifier: Topic :: Software Development :: Libraries :: Python Modules
Requires-Python: >=3.12
Requires-Dist: aiohttp>=3.12.14
Requires-Dist: attrs>=25.3.0
Requires-Dist: h11>=0.16.0
Requires-Dist: humanize>=4.11.0
Requires-Dist: instructor>=1.7.9
Requires-Dist: mcp[cli]>=1.23.0
Requires-Dist: pglast==7.10
Requires-Dist: psycopg-pool>=3.2.6
Requires-Dist: psycopg[binary]>=3.2.6
Requires-Dist: requests>=2.32.4
Requires-Dist: setuptools>=78.1.1
Requires-Dist: starlette>=0.49.1
Requires-Dist: urllib3>=2.6.0
